{"nodes": [{"id": "c_users_user_downloads_awakened_cli_new_awakened_cli_openclaude_main_src_ink_termio_types_ts", "label": "types.ts", "file_type": "code", "source_file": "C:\\Users\\USER\\Downloads\\awakened-cli-new\\awakened-cli\\openclaude-main\\src\\ink\\termio\\types.ts", "source_location": "L1"}, {"id": "termio_types_defaultstyle", "label": "defaultStyle()", "file_type": "code", "source_file": "C:\\Users\\USER\\Downloads\\awakened-cli-new\\awakened-cli\\openclaude-main\\src\\ink\\termio\\types.ts", "source_location": "L68"}, {"id": "termio_types_stylesequal", "label": "stylesEqual()", "file_type": "code", "source_file": "C:\\Users\\USER\\Downloads\\awakened-cli-new\\awakened-cli\\openclaude-main\\src\\ink\\termio\\types.ts", "source_location": "L86"}, {"id": "termio_types_colorsequal", "label": "colorsEqual()", "file_type": "code", "source_file": "C:\\Users\\USER\\Downloads\\awakened-cli-new\\awakened-cli\\openclaude-main\\src\\ink\\termio\\types.ts", "source_location": "L104"}], "edges": [{"source": "c_users_user_downloads_awakened_cli_new_awakened_cli_openclaude_main_src_ink_termio_types_ts", "target": "termio_types_defaultstyle", "relation": "contains", "confidence": "EXTRACTED", "source_file": "C:\\Users\\USER\\Downloads\\awakened-cli-new\\awakened-cli\\openclaude-main\\src\\ink\\termio\\types.ts", "source_location": "L68", "weight": 1.0}, {"source": "c_users_user_downloads_awakened_cli_new_awakened_cli_openclaude_main_src_ink_termio_types_ts", "target": "termio_types_stylesequal", "relation": "contains", "confidence": "EXTRACTED", "source_file": "C:\\Users\\USER\\Downloads\\awakened-cli-new\\awakened-cli\\openclaude-main\\src\\ink\\termio\\types.ts", "source_location": "L86", "weight": 1.0}, {"source": "c_users_user_downloads_awakened_cli_new_awakened_cli_openclaude_main_src_ink_termio_types_ts", "target": "termio_types_colorsequal", "relation": "contains", "confidence": "EXTRACTED", "source_file": "C:\\Users\\USER\\Downloads\\awakened-cli-new\\awakened-cli\\openclaude-main\\src\\ink\\termio\\types.ts", "source_location": "L104", "weight": 1.0}, {"source": "termio_types_stylesequal", "target": "termio_types_colorsequal", "relation": "calls", "context": "call", "confidence": "EXTRACTED", "source_file": "C:\\Users\\USER\\Downloads\\awakened-cli-new\\awakened-cli\\openclaude-main\\src\\ink\\termio\\types.ts", "source_location": "L97", "weight": 1.0}], "raw_calls": []}