{"nodes": [{"id": "c_users_user_downloads_awakened_cli_new_awakened_cli_openclaude_main_src_utils_activitymanager_ts", "label": "activityManager.ts", "file_type": "code", "source_file": "C:\\Users\\USER\\Downloads\\awakened-cli-new\\awakened-cli\\openclaude-main\\src\\utils\\activityManager.ts", "source_location": "L1"}, {"id": "utils_activitymanager_activitymanager", "label": "ActivityManager", "file_type": "code", "source_file": "C:\\Users\\USER\\Downloads\\awakened-cli-new\\awakened-cli\\openclaude-main\\src\\utils\\activityManager.ts", "source_location": "L10"}, {"id": "utils_activitymanager_activitymanager_constructor", "label": ".constructor()", "file_type": "code", "source_file": "C:\\Users\\USER\\Downloads\\awakened-cli-new\\awakened-cli\\openclaude-main\\src\\utils\\activityManager.ts", "source_location": "L24"}, {"id": "utils_activitymanager_activitymanager_getinstance", "label": ".getInstance()", "file_type": "code", "source_file": "C:\\Users\\USER\\Downloads\\awakened-cli-new\\awakened-cli\\openclaude-main\\src\\utils\\activityManager.ts", "source_location": "L29"}, {"id": "utils_activitymanager_activitymanager_resetinstance", "label": ".resetInstance()", "file_type": "code", "source_file": "C:\\Users\\USER\\Downloads\\awakened-cli-new\\awakened-cli\\openclaude-main\\src\\utils\\activityManager.ts", "source_location": "L39"}, {"id": "utils_activitymanager_activitymanager_createinstance", "label": ".createInstance()", "file_type": "code", "source_file": "C:\\Users\\USER\\Downloads\\awakened-cli-new\\awakened-cli\\openclaude-main\\src\\utils\\activityManager.ts", "source_location": "L46"}, {"id": "utils_activitymanager_activitymanager_recorduseractivity", "label": ".recordUserActivity()", "file_type": "code", "source_file": "C:\\Users\\USER\\Downloads\\awakened-cli-new\\awakened-cli\\openclaude-main\\src\\utils\\activityManager.ts", "source_location": "L54"}, {"id": "utils_activitymanager_activitymanager_startcliactivity", "label": ".startCLIActivity()", "file_type": "code", "source_file": "C:\\Users\\USER\\Downloads\\awakened-cli-new\\awakened-cli\\openclaude-main\\src\\utils\\activityManager.ts", "source_location": "L62"}, {"id": "utils_activitymanager_activitymanager_endcliactivity", "label": ".endCLIActivity()", "file_type": "code", "source_file": "C:\\Users\\USER\\Downloads\\awakened-cli-new\\awakened-cli\\openclaude-main\\src\\utils\\activityManager.ts", "source_location": "L82"}, {"id": "utils_activitymanager_activitymanager_trackoperation", "label": ".trackOperation()", "file_type": "code", "source_file": "C:\\Users\\USER\\Downloads\\awakened-cli-new\\awakened-cli\\openclaude-main\\src\\utils\\activityManager.ts", "source_location": "L95"}, {"id": "utils_activitymanager_activitymanager_getactivitystates", "label": ".getActivityStates()", "file_type": "code", "source_file": "C:\\Users\\USER\\Downloads\\awakened-cli-new\\awakened-cli\\openclaude-main\\src\\utils\\activityManager.ts", "source_location": "L110"}], "edges": [{"source": "c_users_user_downloads_awakened_cli_new_awakened_cli_openclaude_main_src_utils_activitymanager_ts", "target": "utils_activitymanager_activitymanager", "relation": "contains", "confidence": "EXTRACTED", "source_file": "C:\\Users\\USER\\Downloads\\awakened-cli-new\\awakened-cli\\openclaude-main\\src\\utils\\activityManager.ts", "source_location": "L10", "weight": 1.0}, {"source": "utils_activitymanager_activitymanager", "target": "utils_activitymanager_activitymanager_constructor", "relation": "method", "confidence": "EXTRACTED", "source_file": "C:\\Users\\USER\\Downloads\\awakened-cli-new\\awakened-cli\\openclaude-main\\src\\utils\\activityManager.ts", "source_location": "L24", "weight": 1.0}, {"source": "utils_activitymanager_activitymanager", "target": "utils_activitymanager_activitymanager_getinstance", "relation": "method", "confidence": "EXTRACTED", "source_file": "C:\\Users\\USER\\Downloads\\awakened-cli-new\\awakened-cli\\openclaude-main\\src\\utils\\activityManager.ts", "source_location": "L29", "weight": 1.0}, {"source": "utils_activitymanager_activitymanager", "target": "utils_activitymanager_activitymanager_resetinstance", "relation": "method", "confidence": "EXTRACTED", "source_file": "C:\\Users\\USER\\Downloads\\awakened-cli-new\\awakened-cli\\openclaude-main\\src\\utils\\activityManager.ts", "source_location": "L39", "weight": 1.0}, {"source": "utils_activitymanager_activitymanager", "target": "utils_activitymanager_activitymanager_createinstance", "relation": "method", "confidence": "EXTRACTED", "source_file": "C:\\Users\\USER\\Downloads\\awakened-cli-new\\awakened-cli\\openclaude-main\\src\\utils\\activityManager.ts", "source_location": "L46", "weight": 1.0}, {"source": "utils_activitymanager_activitymanager", "target": "utils_activitymanager_activitymanager_recorduseractivity", "relation": "method", "confidence": "EXTRACTED", "source_file": "C:\\Users\\USER\\Downloads\\awakened-cli-new\\awakened-cli\\openclaude-main\\src\\utils\\activityManager.ts", "source_location": "L54", "weight": 1.0}, {"source": "utils_activitymanager_activitymanager", "target": "utils_activitymanager_activitymanager_startcliactivity", "relation": "method", "confidence": "EXTRACTED", "source_file": "C:\\Users\\USER\\Downloads\\awakened-cli-new\\awakened-cli\\openclaude-main\\src\\utils\\activityManager.ts", "source_location": "L62", "weight": 1.0}, {"source": "utils_activitymanager_activitymanager", "target": "utils_activitymanager_activitymanager_endcliactivity", "relation": "method", "confidence": "EXTRACTED", "source_file": "C:\\Users\\USER\\Downloads\\awakened-cli-new\\awakened-cli\\openclaude-main\\src\\utils\\activityManager.ts", "source_location": "L82", "weight": 1.0}, {"source": "utils_activitymanager_activitymanager", "target": "utils_activitymanager_activitymanager_trackoperation", "relation": "method", "confidence": "EXTRACTED", "source_file": "C:\\Users\\USER\\Downloads\\awakened-cli-new\\awakened-cli\\openclaude-main\\src\\utils\\activityManager.ts", "source_location": "L95", "weight": 1.0}, {"source": "utils_activitymanager_activitymanager", "target": "utils_activitymanager_activitymanager_getactivitystates", "relation": "method", "confidence": "EXTRACTED", "source_file": "C:\\Users\\USER\\Downloads\\awakened-cli-new\\awakened-cli\\openclaude-main\\src\\utils\\activityManager.ts", "source_location": "L110", "weight": 1.0}, {"source": "utils_activitymanager_activitymanager_startcliactivity", "target": "utils_activitymanager_activitymanager_endcliactivity", "relation": "calls", "context": "call", "confidence": "EXTRACTED", "source_file": "C:\\Users\\USER\\Downloads\\awakened-cli-new\\awakened-cli\\openclaude-main\\src\\utils\\activityManager.ts", "source_location": "L67", "weight": 1.0}, {"source": "utils_activitymanager_activitymanager_trackoperation", "target": "utils_activitymanager_activitymanager_startcliactivity", "relation": "calls", "context": "call", "confidence": "EXTRACTED", "source_file": "C:\\Users\\USER\\Downloads\\awakened-cli-new\\awakened-cli\\openclaude-main\\src\\utils\\activityManager.ts", "source_location": "L99", "weight": 1.0}, {"source": "utils_activitymanager_activitymanager_trackoperation", "target": "utils_activitymanager_activitymanager_endcliactivity", "relation": "calls", "context": "call", "confidence": "EXTRACTED", "source_file": "C:\\Users\\USER\\Downloads\\awakened-cli-new\\awakened-cli\\openclaude-main\\src\\utils\\activityManager.ts", "source_location": "L103", "weight": 1.0}], "raw_calls": [{"caller_nid": "utils_activitymanager_activitymanager_constructor", "callee": "getNow", "is_member_call": true, "source_file": "C:\\Users\\USER\\Downloads\\awakened-cli-new\\awakened-cli\\openclaude-main\\src\\utils\\activityManager.ts", "source_location": "L26"}, {"caller_nid": "utils_activitymanager_activitymanager_recorduseractivity", "callee": "getNow", "is_member_call": true, "source_file": "C:\\Users\\USER\\Downloads\\awakened-cli-new\\awakened-cli\\openclaude-main\\src\\utils\\activityManager.ts", "source_location": "L56"}, {"caller_nid": "utils_activitymanager_activitymanager_startcliactivity", "callee": "has", "is_member_call": true, "source_file": "C:\\Users\\USER\\Downloads\\awakened-cli-new\\awakened-cli\\openclaude-main\\src\\utils\\activityManager.ts", "source_location": "L66"}, {"caller_nid": "utils_activitymanager_activitymanager_startcliactivity", "callee": "add", "is_member_call": true, "source_file": "C:\\Users\\USER\\Downloads\\awakened-cli-new\\awakened-cli\\openclaude-main\\src\\utils\\activityManager.ts", "source_location": "L71"}, {"caller_nid": "utils_activitymanager_activitymanager_startcliactivity", "callee": "getNow", "is_member_call": true, "source_file": "C:\\Users\\USER\\Downloads\\awakened-cli-new\\awakened-cli\\openclaude-main\\src\\utils\\activityManager.ts", "source_location": "L75"}, {"caller_nid": "utils_activitymanager_activitymanager_endcliactivity", "callee": "delete", "is_member_call": true, "source_file": "C:\\Users\\USER\\Downloads\\awakened-cli-new\\awakened-cli\\openclaude-main\\src\\utils\\activityManager.ts", "source_location": "L83"}, {"caller_nid": "utils_activitymanager_activitymanager_endcliactivity", "callee": "getNow", "is_member_call": true, "source_file": "C:\\Users\\USER\\Downloads\\awakened-cli-new\\awakened-cli\\openclaude-main\\src\\utils\\activityManager.ts", "source_location": "L87"}, {"caller_nid": "utils_activitymanager_activitymanager_trackoperation", "callee": "fn", "is_member_call": false, "source_file": "C:\\Users\\USER\\Downloads\\awakened-cli-new\\awakened-cli\\openclaude-main\\src\\utils\\activityManager.ts", "source_location": "L101"}, {"caller_nid": "utils_activitymanager_activitymanager_getactivitystates", "callee": "getNow", "is_member_call": true, "source_file": "C:\\Users\\USER\\Downloads\\awakened-cli-new\\awakened-cli\\openclaude-main\\src\\utils\\activityManager.ts", "source_location": "L115"}]}