{"nodes": [{"id": "c_users_user_downloads_awakened_cli_new_awakened_cli_openclaude_main_src_services_teammemorysync_watcher_ts", "label": "watcher.ts", "file_type": "code", "source_file": "C:\\Users\\USER\\Downloads\\awakened-cli-new\\awakened-cli\\openclaude-main\\src\\services\\teamMemorySync\\watcher.ts", "source_location": "L1"}, {"id": "teammemorysync_watcher_ispermanentfailure", "label": "isPermanentFailure()", "file_type": "code", "source_file": "C:\\Users\\USER\\Downloads\\awakened-cli-new\\awakened-cli\\openclaude-main\\src\\services\\teamMemorySync\\watcher.ts", "source_location": "L61"}, {"id": "teammemorysync_watcher_executepush", "label": "executePush()", "file_type": "code", "source_file": "C:\\Users\\USER\\Downloads\\awakened-cli-new\\awakened-cli\\openclaude-main\\src\\services\\teamMemorySync\\watcher.ts", "source_location": "L84"}, {"id": "teammemorysync_watcher_schedulepush", "label": "schedulePush()", "file_type": "code", "source_file": "C:\\Users\\USER\\Downloads\\awakened-cli-new\\awakened-cli\\openclaude-main\\src\\services\\teamMemorySync\\watcher.ts", "source_location": "L132"}, {"id": "teammemorysync_watcher_startfilewatcher", "label": "startFileWatcher()", "file_type": "code", "source_file": "C:\\Users\\USER\\Downloads\\awakened-cli-new\\awakened-cli\\openclaude-main\\src\\services\\teamMemorySync\\watcher.ts", "source_location": "L167"}, {"id": "teammemorysync_watcher_startteammemorywatcher", "label": "startTeamMemoryWatcher()", "file_type": "code", "source_file": "C:\\Users\\USER\\Downloads\\awakened-cli-new\\awakened-cli\\openclaude-main\\src\\services\\teamMemorySync\\watcher.ts", "source_location": "L252"}, {"id": "teammemorysync_watcher_notifyteammemorywrite", "label": "notifyTeamMemoryWrite()", "file_type": "code", "source_file": "C:\\Users\\USER\\Downloads\\awakened-cli-new\\awakened-cli\\openclaude-main\\src\\services\\teamMemorySync\\watcher.ts", "source_location": "L314"}, {"id": "teammemorysync_watcher_stopteammemorywatcher", "label": "stopTeamMemoryWatcher()", "file_type": "code", "source_file": "C:\\Users\\USER\\Downloads\\awakened-cli-new\\awakened-cli\\openclaude-main\\src\\services\\teamMemorySync\\watcher.ts", "source_location": "L327"}, {"id": "teammemorysync_watcher_resetwatcherstatefortesting", "label": "_resetWatcherStateForTesting()", "file_type": "code", "source_file": "C:\\Users\\USER\\Downloads\\awakened-cli-new\\awakened-cli\\openclaude-main\\src\\services\\teamMemorySync\\watcher.ts", "source_location": "L365"}, {"id": "teammemorysync_watcher_startfilewatcherfortesting", "label": "_startFileWatcherForTesting()", "file_type": "code", "source_file": "C:\\Users\\USER\\Downloads\\awakened-cli-new\\awakened-cli\\openclaude-main\\src\\services\\teamMemorySync\\watcher.ts", "source_location": "L385"}], "edges": [{"source": "c_users_user_downloads_awakened_cli_new_awakened_cli_openclaude_main_src_services_teammemorysync_watcher_ts", "target": "bun_bundle", "relation": "imports_from", "context": "import", "confidence": "EXTRACTED", "source_file": "C:\\Users\\USER\\Downloads\\awakened-cli-new\\awakened-cli\\openclaude-main\\src\\services\\teamMemorySync\\watcher.ts", "source_location": "L10", "weight": 1.0}, {"source": "c_users_user_downloads_awakened_cli_new_awakened_cli_openclaude_main_src_services_teammemorysync_watcher_ts", "target": "fs", "relation": "imports_from", "context": "import", "confidence": "EXTRACTED", "source_file": "C:\\Users\\USER\\Downloads\\awakened-cli-new\\awakened-cli\\openclaude-main\\src\\services\\teamMemorySync\\watcher.ts", "source_location": "L11", "weight": 1.0}, {"source": "c_users_user_downloads_awakened_cli_new_awakened_cli_openclaude_main_src_services_teammemorysync_watcher_ts", "target": "promises", "relation": "imports_from", "context": "import", "confidence": "EXTRACTED", "source_file": "C:\\Users\\USER\\Downloads\\awakened-cli-new\\awakened-cli\\openclaude-main\\src\\services\\teamMemorySync\\watcher.ts", "source_location": "L12", "weight": 1.0}, {"source": "c_users_user_downloads_awakened_cli_new_awakened_cli_openclaude_main_src_services_teammemorysync_watcher_ts", "target": "path", "relation": "imports_from", "context": "import", "confidence": "EXTRACTED", "source_file": "C:\\Users\\USER\\Downloads\\awakened-cli-new\\awakened-cli\\openclaude-main\\src\\services\\teamMemorySync\\watcher.ts", "source_location": "L13", "weight": 1.0}, {"source": "c_users_user_downloads_awakened_cli_new_awakened_cli_openclaude_main_src_services_teammemorysync_watcher_ts", "target": "c_users_user_downloads_awakened_cli_new_awakened_cli_openclaude_main_src_memdir_teammempaths_ts", "relation": "imports_from", "context": "import", "confidence": "EXTRACTED", "source_file": "C:\\Users\\USER\\Downloads\\awakened-cli-new\\awakened-cli\\openclaude-main\\src\\services\\teamMemorySync\\watcher.ts", "source_location": "L14", "weight": 1.0}, {"source": "c_users_user_downloads_awakened_cli_new_awakened_cli_openclaude_main_src_services_teammemorysync_watcher_ts", "target": "memdir_teammempaths_getteammempath", "relation": "imports", "context": "import", "confidence": "EXTRACTED", "source_file": "C:\\Users\\USER\\Downloads\\awakened-cli-new\\awakened-cli\\openclaude-main\\src\\services\\teamMemorySync\\watcher.ts", "source_location": "L14", "weight": 1.0}, {"source": "c_users_user_downloads_awakened_cli_new_awakened_cli_openclaude_main_src_services_teammemorysync_watcher_ts", "target": "memdir_teammempaths_isteammemoryenabled", "relation": "imports", "context": "import", "confidence": "EXTRACTED", "source_file": "C:\\Users\\USER\\Downloads\\awakened-cli-new\\awakened-cli\\openclaude-main\\src\\services\\teamMemorySync\\watcher.ts", "source_location": "L14", "weight": 1.0}, {"source": "c_users_user_downloads_awakened_cli_new_awakened_cli_openclaude_main_src_services_teammemorysync_watcher_ts", "target": "c_users_user_downloads_awakened_cli_new_awakened_cli_openclaude_main_src_utils_cleanupregistry_ts", "relation": "imports_from", "context": "import", "confidence": "EXTRACTED", "source_file": "C:\\Users\\USER\\Downloads\\awakened-cli-new\\awakened-cli\\openclaude-main\\src\\services\\teamMemorySync\\watcher.ts", "source_location": "L18", "weight": 1.0}, {"source": "c_users_user_downloads_awakened_cli_new_awakened_cli_openclaude_main_src_services_teammemorysync_watcher_ts", "target": "utils_cleanupregistry_registercleanup", "relation": "imports", "context": "import", "confidence": "EXTRACTED", "source_file": "C:\\Users\\USER\\Downloads\\awakened-cli-new\\awakened-cli\\openclaude-main\\src\\services\\teamMemorySync\\watcher.ts", "source_location": "L18", "weight": 1.0}, {"source": "c_users_user_downloads_awakened_cli_new_awakened_cli_openclaude_main_src_services_teammemorysync_watcher_ts", "target": "c_users_user_downloads_awakened_cli_new_awakened_cli_openclaude_main_src_utils_debug_ts", "relation": "imports_from", "context": "import", "confidence": "EXTRACTED", "source_file": "C:\\Users\\USER\\Downloads\\awakened-cli-new\\awakened-cli\\openclaude-main\\src\\services\\teamMemorySync\\watcher.ts", "source_location": "L19", "weight": 1.0}, {"source": "c_users_user_downloads_awakened_cli_new_awakened_cli_openclaude_main_src_services_teammemorysync_watcher_ts", "target": "utils_debug_logfordebugging", "relation": "imports", "context": "import", "confidence": "EXTRACTED", "source_file": "C:\\Users\\USER\\Downloads\\awakened-cli-new\\awakened-cli\\openclaude-main\\src\\services\\teamMemorySync\\watcher.ts", "source_location": "L19", "weight": 1.0}, {"source": "c_users_user_downloads_awakened_cli_new_awakened_cli_openclaude_main_src_services_teammemorysync_watcher_ts", "target": "c_users_user_downloads_awakened_cli_new_awakened_cli_openclaude_main_src_utils_errors_ts", "relation": "imports_from", "context": "import", "confidence": "EXTRACTED", "source_file": "C:\\Users\\USER\\Downloads\\awakened-cli-new\\awakened-cli\\openclaude-main\\src\\services\\teamMemorySync\\watcher.ts", "source_location": "L20", "weight": 1.0}, {"source": "c_users_user_downloads_awakened_cli_new_awakened_cli_openclaude_main_src_services_teammemorysync_watcher_ts", "target": "utils_errors_errormessage", "relation": "imports", "context": "import", "confidence": "EXTRACTED", "source_file": "C:\\Users\\USER\\Downloads\\awakened-cli-new\\awakened-cli\\openclaude-main\\src\\services\\teamMemorySync\\watcher.ts", "source_location": "L20", "weight": 1.0}, {"source": "c_users_user_downloads_awakened_cli_new_awakened_cli_openclaude_main_src_services_teammemorysync_watcher_ts", "target": "c_users_user_downloads_awakened_cli_new_awakened_cli_openclaude_main_src_utils_git_ts", "relation": "imports_from", "context": "import", "confidence": "EXTRACTED", "source_file": "C:\\Users\\USER\\Downloads\\awakened-cli-new\\awakened-cli\\openclaude-main\\src\\services\\teamMemorySync\\watcher.ts", "source_location": "L21", "weight": 1.0}, {"source": "c_users_user_downloads_awakened_cli_new_awakened_cli_openclaude_main_src_services_teammemorysync_watcher_ts", "target": "utils_git_getgithubrepo", "relation": "imports", "context": "import", "confidence": "EXTRACTED", "source_file": "C:\\Users\\USER\\Downloads\\awakened-cli-new\\awakened-cli\\openclaude-main\\src\\services\\teamMemorySync\\watcher.ts", "source_location": "L21", "weight": 1.0}, {"source": "c_users_user_downloads_awakened_cli_new_awakened_cli_openclaude_main_src_services_teammemorysync_watcher_ts", "target": "c_users_user_downloads_awakened_cli_new_awakened_cli_openclaude_main_src_services_analytics_index_ts", "relation": "imports_from", "context": "import", "confidence": "EXTRACTED", "source_file": "C:\\Users\\USER\\Downloads\\awakened-cli-new\\awakened-cli\\openclaude-main\\src\\services\\teamMemorySync\\watcher.ts", "source_location": "L22", "weight": 1.0}, {"source": "c_users_user_downloads_awakened_cli_new_awakened_cli_openclaude_main_src_services_teammemorysync_watcher_ts", "target": "analytics_index_analyticsmetadata_i_verified_this_is_not_code_or_filepaths", "relation": "imports", "context": "import", "confidence": "EXTRACTED", "source_file": "C:\\Users\\USER\\Downloads\\awakened-cli-new\\awakened-cli\\openclaude-main\\src\\services\\teamMemorySync\\watcher.ts", "source_location": "L22", "weight": 1.0}, {"source": "c_users_user_downloads_awakened_cli_new_awakened_cli_openclaude_main_src_services_teammemorysync_watcher_ts", "target": "analytics_index_logevent", "relation": "imports", "context": "import", "confidence": "EXTRACTED", "source_file": "C:\\Users\\USER\\Downloads\\awakened-cli-new\\awakened-cli\\openclaude-main\\src\\services\\teamMemorySync\\watcher.ts", "source_location": "L22", "weight": 1.0}, {"source": "c_users_user_downloads_awakened_cli_new_awakened_cli_openclaude_main_src_services_teammemorysync_watcher_ts", "target": "c_users_user_downloads_awakened_cli_new_awakened_cli_openclaude_main_src_services_teammemorysync_index_ts", "relation": "imports_from", "context": "import", "confidence": "EXTRACTED", "source_file": "C:\\Users\\USER\\Downloads\\awakened-cli-new\\awakened-cli\\openclaude-main\\src\\services\\teamMemorySync\\watcher.ts", "source_location": "L26", "weight": 1.0}, {"source": "c_users_user_downloads_awakened_cli_new_awakened_cli_openclaude_main_src_services_teammemorysync_watcher_ts", "target": "teammemorysync_index_createsyncstate", "relation": "imports", "context": "import", "confidence": "EXTRACTED", "source_file": "C:\\Users\\USER\\Downloads\\awakened-cli-new\\awakened-cli\\openclaude-main\\src\\services\\teamMemorySync\\watcher.ts", "source_location": "L26", "weight": 1.0}, {"source": "c_users_user_downloads_awakened_cli_new_awakened_cli_openclaude_main_src_services_teammemorysync_watcher_ts", "target": "teammemorysync_index_isteammemorysyncavailable", "relation": "imports", "context": "import", "confidence": "EXTRACTED", "source_file": "C:\\Users\\USER\\Downloads\\awakened-cli-new\\awakened-cli\\openclaude-main\\src\\services\\teamMemorySync\\watcher.ts", "source_location": "L26", "weight": 1.0}, {"source": "c_users_user_downloads_awakened_cli_new_awakened_cli_openclaude_main_src_services_teammemorysync_watcher_ts", "target": "teammemorysync_index_pullteammemory", "relation": "imports", "context": "import", "confidence": "EXTRACTED", "source_file": "C:\\Users\\USER\\Downloads\\awakened-cli-new\\awakened-cli\\openclaude-main\\src\\services\\teamMemorySync\\watcher.ts", "source_location": "L26", "weight": 1.0}, {"source": "c_users_user_downloads_awakened_cli_new_awakened_cli_openclaude_main_src_services_teammemorysync_watcher_ts", "target": "teammemorysync_index_pushteammemory", "relation": "imports", "context": "import", "confidence": "EXTRACTED", "source_file": "C:\\Users\\USER\\Downloads\\awakened-cli-new\\awakened-cli\\openclaude-main\\src\\services\\teamMemorySync\\watcher.ts", "source_location": "L26", "weight": 1.0}, {"source": "c_users_user_downloads_awakened_cli_new_awakened_cli_openclaude_main_src_services_teammemorysync_watcher_ts", "target": "teammemorysync_index_syncstate", "relation": "imports", "context": "import", "confidence": "EXTRACTED", "source_file": "C:\\Users\\USER\\Downloads\\awakened-cli-new\\awakened-cli\\openclaude-main\\src\\services\\teamMemorySync\\watcher.ts", "source_location": "L26", "weight": 1.0}, {"source": "c_users_user_downloads_awakened_cli_new_awakened_cli_openclaude_main_src_services_teammemorysync_watcher_ts", "target": "c_users_user_downloads_awakened_cli_new_awakened_cli_openclaude_main_src_services_teammemorysync_types_ts", "relation": "imports_from", "context": "import", "confidence": "EXTRACTED", "source_file": "C:\\Users\\USER\\Downloads\\awakened-cli-new\\awakened-cli\\openclaude-main\\src\\services\\teamMemorySync\\watcher.ts", "source_location": "L33", "weight": 1.0}, {"source": "c_users_user_downloads_awakened_cli_new_awakened_cli_openclaude_main_src_services_teammemorysync_watcher_ts", "target": "teammemorysync_types_teammemorysyncpushresult", "relation": "imports", "context": "import", "confidence": "EXTRACTED", "source_file": "C:\\Users\\USER\\Downloads\\awakened-cli-new\\awakened-cli\\openclaude-main\\src\\services\\teamMemorySync\\watcher.ts", "source_location": "L33", "weight": 1.0}, {"source": "c_users_user_downloads_awakened_cli_new_awakened_cli_openclaude_main_src_services_teammemorysync_watcher_ts", "target": "teammemorysync_watcher_ispermanentfailure", "relation": "contains", "confidence": "EXTRACTED", "source_file": "C:\\Users\\USER\\Downloads\\awakened-cli-new\\awakened-cli\\openclaude-main\\src\\services\\teamMemorySync\\watcher.ts", "source_location": "L61", "weight": 1.0}, {"source": "c_users_user_downloads_awakened_cli_new_awakened_cli_openclaude_main_src_services_teammemorysync_watcher_ts", "target": "teammemorysync_watcher_executepush", "relation": "contains", "confidence": "EXTRACTED", "source_file": "C:\\Users\\USER\\Downloads\\awakened-cli-new\\awakened-cli\\openclaude-main\\src\\services\\teamMemorySync\\watcher.ts", "source_location": "L84", "weight": 1.0}, {"source": "c_users_user_downloads_awakened_cli_new_awakened_cli_openclaude_main_src_services_teammemorysync_watcher_ts", "target": "teammemorysync_watcher_schedulepush", "relation": "contains", "confidence": "EXTRACTED", "source_file": "C:\\Users\\USER\\Downloads\\awakened-cli-new\\awakened-cli\\openclaude-main\\src\\services\\teamMemorySync\\watcher.ts", "source_location": "L132", "weight": 1.0}, {"source": "c_users_user_downloads_awakened_cli_new_awakened_cli_openclaude_main_src_services_teammemorysync_watcher_ts", "target": "teammemorysync_watcher_startfilewatcher", "relation": "contains", "confidence": "EXTRACTED", "source_file": "C:\\Users\\USER\\Downloads\\awakened-cli-new\\awakened-cli\\openclaude-main\\src\\services\\teamMemorySync\\watcher.ts", "source_location": "L167", "weight": 1.0}, {"source": "c_users_user_downloads_awakened_cli_new_awakened_cli_openclaude_main_src_services_teammemorysync_watcher_ts", "target": "teammemorysync_watcher_startteammemorywatcher", "relation": "contains", "confidence": "EXTRACTED", "source_file": "C:\\Users\\USER\\Downloads\\awakened-cli-new\\awakened-cli\\openclaude-main\\src\\services\\teamMemorySync\\watcher.ts", "source_location": "L252", "weight": 1.0}, {"source": "c_users_user_downloads_awakened_cli_new_awakened_cli_openclaude_main_src_services_teammemorysync_watcher_ts", "target": "teammemorysync_watcher_notifyteammemorywrite", "relation": "contains", "confidence": "EXTRACTED", "source_file": "C:\\Users\\USER\\Downloads\\awakened-cli-new\\awakened-cli\\openclaude-main\\src\\services\\teamMemorySync\\watcher.ts", "source_location": "L314", "weight": 1.0}, {"source": "c_users_user_downloads_awakened_cli_new_awakened_cli_openclaude_main_src_services_teammemorysync_watcher_ts", "target": "teammemorysync_watcher_stopteammemorywatcher", "relation": "contains", "confidence": "EXTRACTED", "source_file": "C:\\Users\\USER\\Downloads\\awakened-cli-new\\awakened-cli\\openclaude-main\\src\\services\\teamMemorySync\\watcher.ts", "source_location": "L327", "weight": 1.0}, {"source": "c_users_user_downloads_awakened_cli_new_awakened_cli_openclaude_main_src_services_teammemorysync_watcher_ts", "target": "teammemorysync_watcher_resetwatcherstatefortesting", "relation": "contains", "confidence": "EXTRACTED", "source_file": "C:\\Users\\USER\\Downloads\\awakened-cli-new\\awakened-cli\\openclaude-main\\src\\services\\teamMemorySync\\watcher.ts", "source_location": "L365", "weight": 1.0}, {"source": "c_users_user_downloads_awakened_cli_new_awakened_cli_openclaude_main_src_services_teammemorysync_watcher_ts", "target": "teammemorysync_watcher_startfilewatcherfortesting", "relation": "contains", "confidence": "EXTRACTED", "source_file": "C:\\Users\\USER\\Downloads\\awakened-cli-new\\awakened-cli\\openclaude-main\\src\\services\\teamMemorySync\\watcher.ts", "source_location": "L385", "weight": 1.0}, {"source": "teammemorysync_watcher_executepush", "target": "teammemorysync_watcher_ispermanentfailure", "relation": "calls", "context": "call", "confidence": "EXTRACTED", "source_file": "C:\\Users\\USER\\Downloads\\awakened-cli-new\\awakened-cli\\openclaude-main\\src\\services\\teamMemorySync\\watcher.ts", "source_location": "L103", "weight": 1.0}, {"source": "teammemorysync_watcher_startteammemorywatcher", "target": "teammemorysync_watcher_startfilewatcher", "relation": "calls", "context": "call", "confidence": "EXTRACTED", "source_file": "C:\\Users\\USER\\Downloads\\awakened-cli-new\\awakened-cli\\openclaude-main\\src\\services\\teamMemorySync\\watcher.ts", "source_location": "L296", "weight": 1.0}, {"source": "teammemorysync_watcher_notifyteammemorywrite", "target": "teammemorysync_watcher_schedulepush", "relation": "calls", "context": "call", "confidence": "EXTRACTED", "source_file": "C:\\Users\\USER\\Downloads\\awakened-cli-new\\awakened-cli\\openclaude-main\\src\\services\\teamMemorySync\\watcher.ts", "source_location": "L318", "weight": 1.0}, {"source": "teammemorysync_watcher_startfilewatcherfortesting", "target": "teammemorysync_watcher_startfilewatcher", "relation": "calls", "context": "call", "confidence": "EXTRACTED", "source_file": "C:\\Users\\USER\\Downloads\\awakened-cli-new\\awakened-cli\\openclaude-main\\src\\services\\teamMemorySync\\watcher.ts", "source_location": "L386", "weight": 1.0}], "raw_calls": [{"caller_nid": "teammemorysync_watcher_executepush", "callee": "pushTeamMemory", "is_member_call": false, "source_file": "C:\\Users\\USER\\Downloads\\awakened-cli-new\\awakened-cli\\openclaude-main\\src\\services\\teamMemorySync\\watcher.ts", "source_location": "L90"}, {"caller_nid": "teammemorysync_watcher_executepush", "callee": "logForDebugging", "is_member_call": false, "source_file": "C:\\Users\\USER\\Downloads\\awakened-cli-new\\awakened-cli\\openclaude-main\\src\\services\\teamMemorySync\\watcher.ts", "source_location": "L95"}, {"caller_nid": "teammemorysync_watcher_executepush", "callee": "logForDebugging", "is_member_call": false, "source_file": "C:\\Users\\USER\\Downloads\\awakened-cli-new\\awakened-cli\\openclaude-main\\src\\services\\teamMemorySync\\watcher.ts", "source_location": "L100"}, {"caller_nid": "teammemorysync_watcher_executepush", "callee": "logForDebugging", "is_member_call": false, "source_file": "C:\\Users\\USER\\Downloads\\awakened-cli-new\\awakened-cli\\openclaude-main\\src\\services\\teamMemorySync\\watcher.ts", "source_location": "L108"}, {"caller_nid": "teammemorysync_watcher_executepush", "callee": "logEvent", "is_member_call": false, "source_file": "C:\\Users\\USER\\Downloads\\awakened-cli-new\\awakened-cli\\openclaude-main\\src\\services\\teamMemorySync\\watcher.ts", "source_location": "L112"}, {"caller_nid": "teammemorysync_watcher_executepush", "callee": "logForDebugging", "is_member_call": false, "source_file": "C:\\Users\\USER\\Downloads\\awakened-cli-new\\awakened-cli\\openclaude-main\\src\\services\\teamMemorySync\\watcher.ts", "source_location": "L120"}, {"caller_nid": "teammemorysync_watcher_executepush", "callee": "errorMessage", "is_member_call": false, "source_file": "C:\\Users\\USER\\Downloads\\awakened-cli-new\\awakened-cli\\openclaude-main\\src\\services\\teamMemorySync\\watcher.ts", "source_location": "L120"}, {"caller_nid": "teammemorysync_watcher_schedulepush", "callee": "clearTimeout", "is_member_call": false, "source_file": "C:\\Users\\USER\\Downloads\\awakened-cli-new\\awakened-cli\\openclaude-main\\src\\services\\teamMemorySync\\watcher.ts", "source_location": "L136"}, {"caller_nid": "teammemorysync_watcher_schedulepush", "callee": "setTimeout", "is_member_call": false, "source_file": "C:\\Users\\USER\\Downloads\\awakened-cli-new\\awakened-cli\\openclaude-main\\src\\services\\teamMemorySync\\watcher.ts", "source_location": "L138"}, {"caller_nid": "teammemorysync_watcher_startfilewatcher", "callee": "mkdir", "is_member_call": false, "source_file": "C:\\Users\\USER\\Downloads\\awakened-cli-new\\awakened-cli\\openclaude-main\\src\\services\\teamMemorySync\\watcher.ts", "source_location": "L177"}, {"caller_nid": "teammemorysync_watcher_startfilewatcher", "callee": "watch", "is_member_call": false, "source_file": "C:\\Users\\USER\\Downloads\\awakened-cli-new\\awakened-cli\\openclaude-main\\src\\services\\teamMemorySync\\watcher.ts", "source_location": "L179"}, {"caller_nid": "teammemorysync_watcher_startfilewatcher", "callee": "on", "is_member_call": true, "source_file": "C:\\Users\\USER\\Downloads\\awakened-cli-new\\awakened-cli\\openclaude-main\\src\\services\\teamMemorySync\\watcher.ts", "source_location": "L209"}, {"caller_nid": "teammemorysync_watcher_startfilewatcher", "callee": "logForDebugging", "is_member_call": false, "source_file": "C:\\Users\\USER\\Downloads\\awakened-cli-new\\awakened-cli\\openclaude-main\\src\\services\\teamMemorySync\\watcher.ts", "source_location": "L215"}, {"caller_nid": "teammemorysync_watcher_startfilewatcher", "callee": "logForDebugging", "is_member_call": false, "source_file": "C:\\Users\\USER\\Downloads\\awakened-cli-new\\awakened-cli\\openclaude-main\\src\\services\\teamMemorySync\\watcher.ts", "source_location": "L222"}, {"caller_nid": "teammemorysync_watcher_startfilewatcher", "callee": "errorMessage", "is_member_call": false, "source_file": "C:\\Users\\USER\\Downloads\\awakened-cli-new\\awakened-cli\\openclaude-main\\src\\services\\teamMemorySync\\watcher.ts", "source_location": "L223"}, {"caller_nid": "teammemorysync_watcher_startfilewatcher", "callee": "registerCleanup", "is_member_call": false, "source_file": "C:\\Users\\USER\\Downloads\\awakened-cli-new\\awakened-cli\\openclaude-main\\src\\services\\teamMemorySync\\watcher.ts", "source_location": "L228"}, {"caller_nid": "teammemorysync_watcher_startteammemorywatcher", "callee": "feature", "is_member_call": false, "source_file": "C:\\Users\\USER\\Downloads\\awakened-cli-new\\awakened-cli\\openclaude-main\\src\\services\\teamMemorySync\\watcher.ts", "source_location": "L253"}, {"caller_nid": "teammemorysync_watcher_startteammemorywatcher", "callee": "isTeamMemoryEnabled", "is_member_call": false, "source_file": "C:\\Users\\USER\\Downloads\\awakened-cli-new\\awakened-cli\\openclaude-main\\src\\services\\teamMemorySync\\watcher.ts", "source_location": "L256"}, {"caller_nid": "teammemorysync_watcher_startteammemorywatcher", "callee": "isTeamMemorySyncAvailable", "is_member_call": false, "source_file": "C:\\Users\\USER\\Downloads\\awakened-cli-new\\awakened-cli\\openclaude-main\\src\\services\\teamMemorySync\\watcher.ts", "source_location": "L256"}, {"caller_nid": "teammemorysync_watcher_startteammemorywatcher", "callee": "getGithubRepo", "is_member_call": false, "source_file": "C:\\Users\\USER\\Downloads\\awakened-cli-new\\awakened-cli\\openclaude-main\\src\\services\\teamMemorySync\\watcher.ts", "source_location": "L259"}, {"caller_nid": "teammemorysync_watcher_startteammemorywatcher", "callee": "logForDebugging", "is_member_call": false, "source_file": "C:\\Users\\USER\\Downloads\\awakened-cli-new\\awakened-cli\\openclaude-main\\src\\services\\teamMemorySync\\watcher.ts", "source_location": "L261"}, {"caller_nid": "teammemorysync_watcher_startteammemorywatcher", "callee": "createSyncState", "is_member_call": false, "source_file": "C:\\Users\\USER\\Downloads\\awakened-cli-new\\awakened-cli\\openclaude-main\\src\\services\\teamMemorySync\\watcher.ts", "source_location": "L268"}, {"caller_nid": "teammemorysync_watcher_startteammemorywatcher", "callee": "pullTeamMemory", "is_member_call": false, "source_file": "C:\\Users\\USER\\Downloads\\awakened-cli-new\\awakened-cli\\openclaude-main\\src\\services\\teamMemorySync\\watcher.ts", "source_location": "L276"}, {"caller_nid": "teammemorysync_watcher_startteammemorywatcher", "callee": "logForDebugging", "is_member_call": false, "source_file": "C:\\Users\\USER\\Downloads\\awakened-cli-new\\awakened-cli\\openclaude-main\\src\\services\\teamMemorySync\\watcher.ts", "source_location": "L281"}, {"caller_nid": "teammemorysync_watcher_startteammemorywatcher", "callee": "logForDebugging", "is_member_call": false, "source_file": "C:\\Users\\USER\\Downloads\\awakened-cli-new\\awakened-cli\\openclaude-main\\src\\services\\teamMemorySync\\watcher.ts", "source_location": "L287"}, {"caller_nid": "teammemorysync_watcher_startteammemorywatcher", "callee": "errorMessage", "is_member_call": false, "source_file": "C:\\Users\\USER\\Downloads\\awakened-cli-new\\awakened-cli\\openclaude-main\\src\\services\\teamMemorySync\\watcher.ts", "source_location": "L288"}, {"caller_nid": "teammemorysync_watcher_startteammemorywatcher", "callee": "getTeamMemPath", "is_member_call": false, "source_file": "C:\\Users\\USER\\Downloads\\awakened-cli-new\\awakened-cli\\openclaude-main\\src\\services\\teamMemorySync\\watcher.ts", "source_location": "L296"}, {"caller_nid": "teammemorysync_watcher_startteammemorywatcher", "callee": "logEvent", "is_member_call": false, "source_file": "C:\\Users\\USER\\Downloads\\awakened-cli-new\\awakened-cli\\openclaude-main\\src\\services\\teamMemorySync\\watcher.ts", "source_location": "L298"}, {"caller_nid": "teammemorysync_watcher_stopteammemorywatcher", "callee": "clearTimeout", "is_member_call": false, "source_file": "C:\\Users\\USER\\Downloads\\awakened-cli-new\\awakened-cli\\openclaude-main\\src\\services\\teamMemorySync\\watcher.ts", "source_location": "L329"}, {"caller_nid": "teammemorysync_watcher_stopteammemorywatcher", "callee": "close", "is_member_call": true, "source_file": "C:\\Users\\USER\\Downloads\\awakened-cli-new\\awakened-cli\\openclaude-main\\src\\services\\teamMemorySync\\watcher.ts", "source_location": "L333"}, {"caller_nid": "teammemorysync_watcher_stopteammemorywatcher", "callee": "pushTeamMemory", "is_member_call": false, "source_file": "C:\\Users\\USER\\Downloads\\awakened-cli-new\\awakened-cli\\openclaude-main\\src\\services\\teamMemorySync\\watcher.ts", "source_location": "L347"}]}